vsswinir/002_lightweightSR_DIV2K_s64w8_SwinIR-S_x2.pth
vsswinir/002_lightweightSR_DIV2K_s64w8_SwinIR-S_x3.pth
vsswinir/002_lightweightSR_DIV2K_s64w8_SwinIR-S_x4.pth
vsswinir/003_realSR_BSRGAN_DFOWMFC_s64w8_SwinIR-L_x4_GAN.pth
vsswinir/2x_Bubble_AnimeScale_SwinIR_Small_v1.pth
vsswinir/__init__.py
vsswinir/__main__.py
vsswinir/network_swinir.py
vsswinir-2.0.0.dist-info/METADATA
vsswinir-2.0.0.dist-info/WHEEL
vsswinir-2.0.0.dist-info/licenses/LICENSE
vsswinir-2.0.0.dist-info/RECORD
