Metadata-Version: 2.1
Name: vsswinir
Version: 2.0.0
Summary: SwinIR function for VapourSynth
Project-URL: Homepage, https://github.com/HolyWu/vs-swinir
Project-URL: Bug Tracker, https://github.com/HolyWu/vs-swinir/issues
Author-email: HolyWu <holywu@gmail.com>
License:                                  Apache License
License-File: LICENSE
Keywords: SwinIR,VapourSynth
Classifier: License :: OSI Approved :: Apache Software License
Classifier: Operating System :: OS Independent
Classifier: Programming Language :: Python :: 3.10
Classifier: Topic :: Multimedia :: Video
Requires-Python: >=3.10
Requires-Dist: numpy
Requires-Dist: requests
Requires-Dist: timm
Requires-Dist: torch>=1.13.0
Requires-Dist: tqdm
Requires-Dist: vapoursynth>=55
